rdsolver/__init__.py
rdsolver/models.py
rdsolver/rd.py
rdsolver/utils.py
rdsolver/viz.py
rdsolver-0.1.6.dist-info/LICENSE
rdsolver-0.1.6.dist-info/METADATA
rdsolver-0.1.6.dist-info/WHEEL
rdsolver-0.1.6.dist-info/top_level.txt
rdsolver-0.1.6.dist-info/RECORD
