Metadata-Version: 2.1
Name: rdsolver
Version: 0.1.6
Summary: Solver for 2D reaction-diffusion systems.
Home-page: https://github.com/justinbois/rdsolver
Author: Justin Bois
Author-email: bois@caltech.edu
License: MIT license
Keywords: rdsolver
Classifier: Development Status :: 2 - Pre-Alpha
Classifier: Intended Audience :: Developers
Classifier: License :: OSI Approved :: MIT License
Classifier: Natural Language :: English
Classifier: Programming Language :: Python :: 3.6
Classifier: Programming Language :: Python :: 3.7
Classifier: Programming Language :: Python :: 3.8
Classifier: Programming Language :: Python :: 3.9
Classifier: Programming Language :: Python :: 3.10
License-File: LICENSE
Requires-Dist: numpy
Requires-Dist: scipy
Requires-Dist: numba
Requires-Dist: bokeh
Requires-Dist: tqdm
